Metadata-Version: 1.0
Name: fairput
Version: 0.0.1
Summary: Fair Machine Learning Outputs
Home-page: https://github.com/firmai/fairput
Author: snowde
Author-email: d.snow@firmai.org
License: MIT
Platform: UNKNOWN
